{
    "map":
        {"grid": [[{"layers": [{"0": ["nonmob", {"permeability": 0, "id": "default:nonmob:stone"}]}, {"0": ["nonmob", {"permeability": 0, "id": "default:nonmob:stone"}]}]}, {"layers": [{"0": ["nonmob", {"permeability": 0, "id": "default:nonmob:stone"}]}, {"0": ["nonmob", {"permeability": 0, "id": "default:nonmob:stone"}]}]}, {"layers": [{"0": ["nonmob", {"permeability": 0, "id": "default:nonmob:stone"}]}, {"0": ["nonmob", {"permeability": 0, "id": "default:nonmob:stone"}]}]}, {"layers": [{"0": ["nonmob", {"permeability": 0, "id": "default:nonmob:stone"}]}, {"0": ["nonmob", {"permeability": 0, "id": "default:nonmob:stone"}]}]}, {"layers": [{"0": ["nonmob", {"permeability": 0, "id": "default:nonmob:stone"}]}, {"0": ["nonmob", {"permeability": 0, "id": "default:nonmob:stone"}]}]}, {"layers": [{"0": ["nonmob", {"permeability": 0, "id": "default:nonmob:stone"}]}, {"0": ["nonmob", {"permeability": 0, "id": "default:nonmob:stone"}]}]}, {"layers": [{"0": ["nonmob", {"permeability": 0, "id": "default:nonmob:stone"}]}, {"0": ["nonmob", {"permeability": 0, "id": "default:nonmob:stone"}]}]}, {"layers": [{"0": ["nonmob", {"permeability": 0, "id": "default:nonmob:stone"}]}, {"0": ["nonmob", {"permeability": 0, "id": "default:nonmob:stone"}]}]}, {"layers": [{"0": ["nonmob", {"permeability": 0, "id": "default:nonmob:stone"}]}, {"0": ["nonmob", {"permeability": 0, "id": "default:nonmob:stone"}]}]}, {"layers": [{"0": ["nonmob", {"permeability": 0, "id": "default:nonmob:stone"}]}, {"0": ["nonmob", {"permeability": 0, "id": "default:nonmob:stone"}]}]}, {"layers": [{"0": ["nonmob", {"permeability": 0, "id": "default:nonmob:stone"}]}, {"0": ["nonmob", {"permeability": 0, "id": "default:nonmob:stone"}]}]}, {"layers": [{"0": ["nonmob", {"permeability": 0, "id": "default:nonmob:stone"}]}, {"0": ["nonmob", {"permeability": 0, "id": "default:nonmob:stone"}]}]}, {"layers": [{"0": ["nonmob", {"permeability": 0, "id": "default:nonmob:stone"}]}, {"0": ["nonmob", {"permeability": 0, "id": "default:nonmob:stone"}]}]}, {"layers": [{"0": ["nonmob", {"permeability": 0, "id": "default:nonmob:stone"}]}, {"0": ["nonmob", {"permeability": 0, "id": "default:nonmob:stone"}]}]}, {"layers": [{"0": ["nonmob", {"permeability": 0, "id": "default:nonmob:stone"}]}, {"0": ["nonmob", {"permeability": 0, "id": "default:nonmob:stone"}]}]}, {"layers": [{"0": ["nonmob", {"permeability": 0, "id": "default:nonmob:stone"}]}, {"0": ["nonmob", {"permeability": 0, "id": "default:nonmob:stone"}]}]}], [{"layers": [{"0": ["nonmob", {"permeability": 0, "id": "default:nonmob:stone"}]}, {"0": ["nonmob", {"permeability": 0, "id": "default:nonmob:stone"}]}]}, {"layers": [{"0": ["nonmob", {"permeability": 0, "id": "default:nonmob:grass"}]}]}, {"layers": [{"0": ["nonmob", {"permeability": 0, "id": "default:nonmob:grass"}]}]}, {"layers": [{"0": ["nonmob", {"permeability": 0, "id": "default:nonmob:grass"}]}]}, {"layers": [{"0": ["nonmob", {"permeability": 0, "id": "default:nonmob:grass"}]}]}, {"layers": [{"0": ["nonmob", {"permeability": 0, "id": "default:nonmob:grass"}]}]}, {"layers": [{"0": ["nonmob", {"permeability": 0, "id": "default:nonmob:grass"}]}]}, {"layers": [{"0": ["nonmob", {"permeability": 0, "id": "default:nonmob:grass"}]}]}, {"layers": [{"0": ["nonmob", {"permeability": 0, "id": "default:nonmob:grass"}]}]}, {"layers": [{"0": ["nonmob", {"permeability": 0, "id": "default:nonmob:grass"}]}]}, {"layers": [{"0": ["nonmob", {"permeability": 0, "id": "default:nonmob:grass"}]}]}, {"layers": [{"0": ["nonmob", {"permeability": 0, "id": "default:nonmob:grass"}]}]}, {"layers": [{"0": ["nonmob", {"permeability": 0, "id": "default:nonmob:grass"}]}]}, {"layers": [{"0": ["nonmob", {"permeability": 0, "id": "default:nonmob:grass"}]}]}, {"layers": [{"0": ["nonmob", {"permeability": 0, "id": "default:nonmob:grass"}]}]}, {"layers": [{"0": ["nonmob", {"permeability": 0, "id": "default:nonmob:stone"}]}, {"0": ["nonmob", {"permeability": 0, "id": "default:nonmob:stone"}]}]}], [{"layers": [{"0": ["nonmob", {"permeability": 0, "id": "default:nonmob:stone"}]}, {"0": ["nonmob", {"permeability": 0, "id": "default:nonmob:stone"}]}]}, {"layers": [{"0": ["nonmob", {"permeability": 0, "id": "default:nonmob:grass"}]}]}, {"layers": [{"0": ["nonmob", {"permeability": 0, "id": "default:nonmob:grass"}]}]}, {"layers": [{"0": ["nonmob", {"permeability": 0, "id": "default:nonmob:grass"}]}]}, {"layers": [{"0": ["nonmob", {"permeability": 0, "id": "default:nonmob:grass"}]}]}, {"layers": [{"0": ["nonmob", {"permeability": 0, "id": "default:nonmob:grass"}]}]}, {"layers": [{"0": ["nonmob", {"permeability": 0, "id": "default:nonmob:grass"}]}]}, {"layers": [{"0": ["nonmob", {"permeability": 0, "id": "default:nonmob:grass"}]}]}, {"layers": [{"0": ["nonmob", {"permeability": 0, "id": "default:nonmob:grass"}]}]}, {"layers": [{"0": ["nonmob", {"permeability": 0, "id": "default:nonmob:grass"}]}]}, {"layers": [{"0": ["nonmob", {"permeability": 0, "id": "default:nonmob:grass"}]}]}, {"layers": [{"0": ["nonmob", {"permeability": 0, "id": "default:nonmob:grass"}]}]}, {"layers": [{"0": ["nonmob", {"permeability": 0, "id": "default:nonmob:grass"}]}]}, {"layers": [{"0": ["nonmob", {"permeability": 0, "id": "default:nonmob:grass"}]}]}, {"layers": [{"0": ["nonmob", {"permeability": 0, "id": "default:nonmob:grass"}]}]}, {"layers": [{"0": ["nonmob", {"permeability": 0, "id": "default:nonmob:stone"}]}, {"0": ["nonmob", {"permeability": 0, "id": "default:nonmob:stone"}]}]}], [{"layers": [{"0": ["nonmob", {"permeability": 0, "id": "default:nonmob:stone"}]}, {"0": ["nonmob", {"permeability": 0, "id": "default:nonmob:stone"}]}]}, {"layers": [{"0": ["nonmob", {"permeability": 0, "id": "default:nonmob:grass"}]}]}, {"layers": [{"0": ["nonmob", {"permeability": 0, "id": "default:nonmob:grass"}]}]}, {"layers": [{"0": ["nonmob", {"permeability": 0, "id": "default:nonmob:grass"}]}]}, {"layers": [{"0": ["nonmob", {"permeability": 0, "id": "default:nonmob:grass"}]}]}, {"layers": [{"0": ["nonmob", {"permeability": 0, "id": "default:nonmob:grass"}]}]}, {"layers": [{"0": ["nonmob", {"permeability": 0, "id": "default:nonmob:grass"}]}]}, {"layers": [{"0": ["nonmob", {"permeability": 0, "id": "default:nonmob:grass"}]}]}, {"layers": [{"0": ["nonmob", {"permeability": 0, "id": "default:nonmob:grass"}]}]}, {"layers": [{"0": ["nonmob", {"permeability": 0, "id": "default:nonmob:grass"}]}]}, {"layers": [{"0": ["nonmob", {"permeability": 0, "id": "default:nonmob:grass"}]}]}, {"layers": [{"0": ["nonmob", {"permeability": 0, "id": "default:nonmob:grass"}]}]}, {"layers": [{"0": ["nonmob", {"permeability": 0, "id": "default:nonmob:grass"}]}]}, {"layers": [{"0": ["nonmob", {"permeability": 0, "id": "default:nonmob:grass"}]}]}, {"layers": [{"0": ["nonmob", {"permeability": 0, "id": "default:nonmob:grass"}]}]}, {"layers": [{"0": ["nonmob", {"permeability": 0, "id": "default:nonmob:stone"}]}, {"0": ["nonmob", {"permeability": 0, "id": "default:nonmob:stone"}]}]}], [{"layers": [{"0": ["nonmob", {"permeability": 0, "id": "default:nonmob:stone"}]}, {"0": ["nonmob", {"permeability": 0, "id": "default:nonmob:stone"}]}]}, {"layers": [{"0": ["nonmob", {"permeability": 0, "id": "default:nonmob:grass"}]}]}, {"layers": [{"0": ["nonmob", {"permeability": 0, "id": "default:nonmob:grass"}]}]}, {"layers": [{"0": ["nonmob", {"permeability": 0, "id": "default:nonmob:grass"}]}]}, {"layers": [{"0": ["nonmob", {"permeability": 0, "id": "default:nonmob:stone"}]}, {"0": ["nonmob", {"permeability": 0, "id": "default:nonmob:stone"}]}]}, {"layers": [{"0": ["nonmob", {"permeability": 0, "id": "default:nonmob:grass"}]}]}, {"layers": [{"0": ["nonmob", {"permeability": 0, "id": "default:nonmob:grass"}]}]}, {"layers": [{"0": ["nonmob", {"permeability": 0, "id": "default:nonmob:grass"}]}]}, {"layers": [{"0": ["nonmob", {"permeability": 0, "id": "default:nonmob:grass"}]}]}, {"layers": [{"0": ["nonmob", {"permeability": 0, "id": "default:nonmob:grass"}]}]}, {"layers": [{"0": ["nonmob", {"permeability": 0, "id": "default:nonmob:grass"}]}]}, {"layers": [{"0": ["nonmob", {"permeability": 0, "id": "default:nonmob:grass"}]}]}, {"layers": [{"0": ["nonmob", {"permeability": 0, "id": "default:nonmob:grass"}]}]}, {"layers": [{"0": ["nonmob", {"permeability": 0, "id": "default:nonmob:grass"}]}]}, {"layers": [{"0": ["nonmob", {"permeability": 0, "id": "default:nonmob:grass"}]}]}, {"layers": [{"0": ["nonmob", {"permeability": 0, "id": "default:nonmob:stone"}]}, {"0": ["nonmob", {"permeability": 0, "id": "default:nonmob:stone"}]}]}], [{"layers": [{"0": ["nonmob", {"permeability": 0, "id": "default:nonmob:stone"}]}, {"0": ["nonmob", {"permeability": 0, "id": "default:nonmob:stone"}]}]}, {"layers": [{"0": ["nonmob", {"permeability": 0, "id": "default:nonmob:grass"}]}]}, {"layers": [{"0": ["nonmob", {"permeability": 0, "id": "default:nonmob:grass"}]}]}, {"layers": [{"0": ["nonmob", {"permeability": 0, "id": "default:nonmob:grass"}]}]}, {"layers": [{"0": ["nonmob", {"permeability": 0, "id": "default:nonmob:grass"}]}]}, {"layers": [{"0": ["nonmob", {"permeability": 0, "id": "default:nonmob:grass"}]}]}, {"layers": [{"0": ["nonmob", {"permeability": 0, "id": "default:nonmob:grass"}]}]}, {"layers": [{"0": ["nonmob", {"permeability": 0, "id": "default:nonmob:grass"}]}]}, {"layers": [{"0": ["nonmob", {"permeability": 0, "id": "default:nonmob:grass"}]}]}, {"layers": [{"0": ["nonmob", {"permeability": 0, "id": "default:nonmob:grass"}]}]}, {"layers": [{"0": ["nonmob", {"permeability": 0, "id": "default:nonmob:grass"}]}]}, {"layers": [{"0": ["nonmob", {"permeability": 0, "id": "default:nonmob:grass"}]}]}, {"layers": [{"0": ["nonmob", {"permeability": 0, "id": "default:nonmob:grass"}]}]}, {"layers": [{"0": ["nonmob", {"permeability": 0, "id": "default:nonmob:grass"}]}]}, {"layers": [{"0": ["nonmob", {"permeability": 0, "id": "default:nonmob:grass"}]}]}, {"layers": [{"0": ["nonmob", {"permeability": 0, "id": "default:nonmob:stone"}]}, {"0": ["nonmob", {"permeability": 0, "id": "default:nonmob:stone"}]}]}], [{"layers": [{"0": ["nonmob", {"permeability": 0, "id": "default:nonmob:stone"}]}, {"0": ["nonmob", {"permeability": 0, "id": "default:nonmob:stone"}]}]}, {"layers": [{"0": ["nonmob", {"permeability": 0, "id": "default:nonmob:grass"}]}]}, {"layers": [{"0": ["nonmob", {"permeability": 0, "id": "default:nonmob:grass"}]}]}, {"layers": [{"0": ["nonmob", {"permeability": 0, "id": "default:nonmob:grass"}]}]}, {"layers": [{"0": ["nonmob", {"permeability": 0, "id": "default:nonmob:grass"}]}]}, {"layers": [{"0": ["nonmob", {"permeability": 0, "id": "default:nonmob:grass"}]}]}, {"layers": [{"0": ["nonmob", {"permeability": 0, "id": "default:nonmob:grass"}]}]}, {"layers": [{"0": ["nonmob", {"permeability": 0, "id": "default:nonmob:grass"}]}]}, {"layers": [{"0": ["nonmob", {"permeability": 0, "id": "default:nonmob:grass"}]}]}, {"layers": [{"0": ["nonmob", {"permeability": 0, "id": "default:nonmob:grass"}]}]}, {"layers": [{"0": ["nonmob", {"permeability": 0, "id": "default:nonmob:grass"}]}]}, {"layers": [{"0": ["nonmob", {"permeability": 0, "id": "default:nonmob:grass"}]}]}, {"layers": [{"0": ["nonmob", {"permeability": 0, "id": "default:nonmob:grass"}]}]}, {"layers": [{"0": ["nonmob", {"permeability": 0, "id": "default:nonmob:grass"}]}]}, {"layers": [{"0": ["nonmob", {"permeability": 0, "id": "default:nonmob:grass"}]}]}, {"layers": [{"0": ["nonmob", {"permeability": 0, "id": "default:nonmob:stone"}]}, {"0": ["nonmob", {"permeability": 0, "id": "default:nonmob:stone"}]}]}], [{"layers": [{"0": ["nonmob", {"permeability": 0, "id": "default:nonmob:stone"}]}, {"0": ["nonmob", {"permeability": 0, "id": "default:nonmob:stone"}]}]}, {"layers": [{"0": ["nonmob", {"permeability": 0, "id": "default:nonmob:grass"}]}]}, {"layers": [{"0": ["nonmob", {"permeability": 0, "id": "default:nonmob:grass"}]}]}, {"layers": [{"0": ["nonmob", {"permeability": 0, "id": "default:nonmob:grass"}]}]}, {"layers": [{"0": ["nonmob", {"permeability": 0, "id": "default:nonmob:grass"}]}]}, {"layers": [{"0": ["nonmob", {"permeability": 0, "id": "default:nonmob:grass"}]}]}, {"layers": [{"0": ["nonmob", {"permeability": 0, "id": "default:nonmob:grass"}]}]}, {"layers": [{"0": ["nonmob", {"permeability": 0, "id": "default:nonmob:grass"}]}]}, {"layers": [{"0": ["nonmob", {"permeability": 0, "id": "default:nonmob:grass"}]}]}, {"layers": [{"0": ["nonmob", {"permeability": 0, "id": "default:nonmob:grass"}]}]}, {"layers": [{"0": ["nonmob", {"permeability": 0, "id": "default:nonmob:grass"}]}]}, {"layers": [{"0": ["nonmob", {"permeability": 0, "id": "default:nonmob:grass"}]}]}, {"layers": [{"0": ["nonmob", {"permeability": 0, "id": "default:nonmob:grass"}]}]}, {"layers": [{"0": ["nonmob", {"permeability": 0, "id": "default:nonmob:grass"}]}]}, {"layers": [{"0": ["nonmob", {"permeability": 0, "id": "default:nonmob:grass"}]}]}, {"layers": [{"0": ["nonmob", {"permeability": 0, "id": "default:nonmob:stone"}]}, {"0": ["nonmob", {"permeability": 0, "id": "default:nonmob:stone"}]}]}], [{"layers": [{"0": ["nonmob", {"permeability": 0, "id": "default:nonmob:stone"}]}, {"0": ["nonmob", {"permeability": 0, "id": "default:nonmob:stone"}]}]}, {"layers": [{"0": ["nonmob", {"permeability": 0, "id": "default:nonmob:grass"}]}]}, {"layers": [{"0": ["nonmob", {"permeability": 0, "id": "default:nonmob:grass"}]}]}, {"layers": [{"0": ["nonmob", {"permeability": 0, "id": "default:nonmob:grass"}]}]}, {"layers": [{"0": ["nonmob", {"permeability": 0, "id": "default:nonmob:grass"}]}]}, {"layers": [{"0": ["nonmob", {"permeability": 0, "id": "default:nonmob:grass"}]}]}, {"layers": [{"0": ["nonmob", {"permeability": 0, "id": "default:nonmob:grass"}]}]}, {"layers": [{"0": ["nonmob", {"permeability": 0, "id": "default:nonmob:grass"}]}]}, {"layers": [{"0": ["nonmob", {"permeability": 0, "id": "default:nonmob:grass"}]}, 
        {"1": ["mob", {"permeability": 1, "id": "default:mob:player", "ai": "default:ai:player", "next_turn": null, "actions": [
            "default:action:move_north", "default:action:move_northeast", "default:action:move_east", "default:action:move_southeast",
            "default:action:move_south", "default:action:move_southwest", "default:action:move_west", "default:action:move_northwest"
        ]}]}]}, 
        {"layers": [{"0": ["nonmob", {"permeability": 0, "id": "default:nonmob:grass"}]}]}, {"layers": [{"0": ["nonmob", {"permeability": 0, "id": "default:nonmob:grass"}]}]}, {"layers": [{"0": ["nonmob", {"permeability": 0, "id": "default:nonmob:grass"}]}]}, {"layers": [{"0": ["nonmob", {"permeability": 0, "id": "default:nonmob:grass"}]}]}, {"layers": [{"0": ["nonmob", {"permeability": 0, "id": "default:nonmob:grass"}]}]}, {"layers": [{"0": ["nonmob", {"permeability": 0, "id": "default:nonmob:grass"}]}]}, {"layers": [{"0": ["nonmob", {"permeability": 0, "id": "default:nonmob:stone"}]}, {"0": ["nonmob", {"permeability": 0, "id": "default:nonmob:stone"}]}]}], [{"layers": [{"0": ["nonmob", {"permeability": 0, "id": "default:nonmob:stone"}]}, {"0": ["nonmob", {"permeability": 0, "id": "default:nonmob:stone"}]}]}, {"layers": [{"0": ["nonmob", {"permeability": 0, "id": "default:nonmob:grass"}]}]}, {"layers": [{"0": ["nonmob", {"permeability": 0, "id": "default:nonmob:grass"}]}]}, {"layers": [{"0": ["nonmob", {"permeability": 0, "id": "default:nonmob:grass"}]}]}, {"layers": [{"0": ["nonmob", {"permeability": 0, "id": "default:nonmob:grass"}]}]}, {"layers": [{"0": ["nonmob", {"permeability": 0, "id": "default:nonmob:grass"}]}]}, {"layers": [{"0": ["nonmob", {"permeability": 0, "id": "default:nonmob:grass"}]}]}, {"layers": [{"0": ["nonmob", {"permeability": 0, "id": "default:nonmob:grass"}]}]}, {"layers": [{"0": ["nonmob", {"permeability": 0, "id": "default:nonmob:grass"}]}]}, {"layers": [{"0": ["nonmob", {"permeability": 0, "id": "default:nonmob:grass"}]}]}, {"layers": [{"0": ["nonmob", {"permeability": 0, "id": "default:nonmob:grass"}]}]}, {"layers": [{"0": ["nonmob", {"permeability": 0, "id": "default:nonmob:grass"}]}]}, {"layers": [{"0": ["nonmob", {"permeability": 0, "id": "default:nonmob:grass"}]}]}, {"layers": [{"0": ["nonmob", {"permeability": 0, "id": "default:nonmob:grass"}]}]}, {"layers": [{"0": ["nonmob", {"permeability": 0, "id": "default:nonmob:grass"}]}]}, {"layers": [{"0": ["nonmob", {"permeability": 0, "id": "default:nonmob:stone"}]}, {"0": ["nonmob", {"permeability": 0, "id": "default:nonmob:stone"}]}]}], [{"layers": [{"0": ["nonmob", {"permeability": 0, "id": "default:nonmob:stone"}]}, {"0": ["nonmob", {"permeability": 0, "id": "default:nonmob:stone"}]}]}, {"layers": [{"0": ["nonmob", {"permeability": 0, "id": "default:nonmob:grass"}]}]}, {"layers": [{"0": ["nonmob", {"permeability": 0, "id": "default:nonmob:grass"}]}]}, {"layers": [{"0": ["nonmob", {"permeability": 0, "id": "default:nonmob:grass"}]}]}, {"layers": [{"0": ["nonmob", {"permeability": 0, "id": "default:nonmob:grass"}]}]}, {"layers": [{"0": ["nonmob", {"permeability": 0, "id": "default:nonmob:grass"}]}]}, {"layers": [{"0": ["nonmob", {"permeability": 0, "id": "default:nonmob:grass"}]}]}, {"layers": [{"0": ["nonmob", {"permeability": 0, "id": "default:nonmob:grass"}]}]}, {"layers": [{"0": ["nonmob", {"permeability": 0, "id": "default:nonmob:grass"}]}]}, {"layers": [{"0": ["nonmob", {"permeability": 0, "id": "default:nonmob:grass"}]}]}, {"layers": [{"0": ["nonmob", {"permeability": 0, "id": "default:nonmob:grass"}]}]}, {"layers": [{"0": ["nonmob", {"permeability": 0, "id": "default:nonmob:grass"}]}]}, {"layers": [{"0": ["nonmob", {"permeability": 0, "id": "default:nonmob:grass"}]}]}, {"layers": [{"0": ["nonmob", {"permeability": 0, "id": "default:nonmob:grass"}]}]}, {"layers": [{"0": ["nonmob", {"permeability": 0, "id": "default:nonmob:grass"}]}]}, {"layers": [{"0": ["nonmob", {"permeability": 0, "id": "default:nonmob:stone"}]}, {"0": ["nonmob", {"permeability": 0, "id": "default:nonmob:stone"}]}]}], [{"layers": [{"0": ["nonmob", {"permeability": 0, "id": "default:nonmob:stone"}]}, {"0": ["nonmob", {"permeability": 0, "id": "default:nonmob:stone"}]}]}, {"layers": [{"0": ["nonmob", {"permeability": 0, "id": "default:nonmob:grass"}]}]}, {"layers": [{"0": ["nonmob", {"permeability": 0, "id": "default:nonmob:grass"}]}]}, {"layers": [{"0": ["nonmob", {"permeability": 0, "id": "default:nonmob:grass"}]}]}, {"layers": [{"0": ["nonmob", {"permeability": 0, "id": "default:nonmob:grass"}]}]}, {"layers": [{"0": ["nonmob", {"permeability": 0, "id": "default:nonmob:grass"}]}]}, {"layers": [{"0": ["nonmob", {"permeability": 0, "id": "default:nonmob:grass"}]}]}, {"layers": [{"0": ["nonmob", {"permeability": 0, "id": "default:nonmob:grass"}]}]}, {"layers": [{"0": ["nonmob", {"permeability": 0, "id": "default:nonmob:grass"}]}]}, {"layers": [{"0": ["nonmob", {"permeability": 0, "id": "default:nonmob:grass"}]}]}, {"layers": [{"0": ["nonmob", {"permeability": 0, "id": "default:nonmob:grass"}]}]}, {"layers": [{"0": ["nonmob", {"permeability": 0, "id": "default:nonmob:grass"}]}]}, {"layers": [{"0": ["nonmob", {"permeability": 0, "id": "default:nonmob:grass"}]}]}, {"layers": [{"0": ["nonmob", {"permeability": 0, "id": "default:nonmob:grass"}]}]}, {"layers": [{"0": ["nonmob", {"permeability": 0, "id": "default:nonmob:grass"}]}]}, {"layers": [{"0": ["nonmob", {"permeability": 0, "id": "default:nonmob:stone"}]}, {"0": ["nonmob", {"permeability": 0, "id": "default:nonmob:stone"}]}]}], [{"layers": [{"0": ["nonmob", {"permeability": 0, "id": "default:nonmob:stone"}]}, {"0": ["nonmob", {"permeability": 0, "id": "default:nonmob:stone"}]}]}, {"layers": [{"0": ["nonmob", {"permeability": 0, "id": "default:nonmob:grass"}]}]}, {"layers": [{"0": ["nonmob", {"permeability": 0, "id": "default:nonmob:grass"}]}]}, {"layers": [{"0": ["nonmob", {"permeability": 0, "id": "default:nonmob:grass"}]}]}, {"layers": [{"0": ["nonmob", {"permeability": 0, "id": "default:nonmob:grass"}]}]}, {"layers": [{"0": ["nonmob", {"permeability": 0, "id": "default:nonmob:grass"}]}]}, {"layers": [{"0": ["nonmob", {"permeability": 0, "id": "default:nonmob:grass"}]}]}, {"layers": [{"0": ["nonmob", {"permeability": 0, "id": "default:nonmob:grass"}]}]}, {"layers": [{"0": ["nonmob", {"permeability": 0, "id": "default:nonmob:grass"}]}]}, {"layers": [{"0": ["nonmob", {"permeability": 0, "id": "default:nonmob:grass"}]}]}, {"layers": [{"0": ["nonmob", {"permeability": 0, "id": "default:nonmob:grass"}]}]}, {"layers": [{"0": ["nonmob", {"permeability": 0, "id": "default:nonmob:grass"}]}]}, {"layers": [{"0": ["nonmob", {"permeability": 0, "id": "default:nonmob:grass"}]}]}, {"layers": [{"0": ["nonmob", {"permeability": 0, "id": "default:nonmob:grass"}]}]}, {"layers": [{"0": ["nonmob", {"permeability": 0, "id": "default:nonmob:grass"}]}]}, {"layers": [{"0": ["nonmob", {"permeability": 0, "id": "default:nonmob:stone"}]}, {"0": ["nonmob", {"permeability": 0, "id": "default:nonmob:stone"}]}]}], [{"layers": [{"0": ["nonmob", {"permeability": 0, "id": "default:nonmob:stone"}]}, {"0": ["nonmob", {"permeability": 0, "id": "default:nonmob:stone"}]}]}, {"layers": [{"0": ["nonmob", {"permeability": 0, "id": "default:nonmob:grass"}]}]}, {"layers": [{"0": ["nonmob", {"permeability": 0, "id": "default:nonmob:grass"}]}]}, {"layers": [{"0": ["nonmob", {"permeability": 0, "id": "default:nonmob:grass"}]}]}, {"layers": [{"0": ["nonmob", {"permeability": 0, "id": "default:nonmob:grass"}]}]}, {"layers": [{"0": ["nonmob", {"permeability": 0, "id": "default:nonmob:grass"}]}]}, {"layers": [{"0": ["nonmob", {"permeability": 0, "id": "default:nonmob:grass"}]}]}, {"layers": [{"0": ["nonmob", {"permeability": 0, "id": "default:nonmob:grass"}]}]}, {"layers": [{"0": ["nonmob", {"permeability": 0, "id": "default:nonmob:grass"}]}]}, {"layers": [{"0": ["nonmob", {"permeability": 0, "id": "default:nonmob:grass"}]}]}, {"layers": [{"0": ["nonmob", {"permeability": 0, "id": "default:nonmob:grass"}]}]}, {"layers": [{"0": ["nonmob", {"permeability": 0, "id": "default:nonmob:grass"}]}]}, {"layers": [{"0": ["nonmob", {"permeability": 0, "id": "default:nonmob:grass"}]}]}, {"layers": [{"0": ["nonmob", {"permeability": 0, "id": "default:nonmob:grass"}]}]}, {"layers": [{"0": ["nonmob", {"permeability": 0, "id": "default:nonmob:grass"}]}]}, {"layers": [{"0": ["nonmob", {"permeability": 0, "id": "default:nonmob:stone"}]}, {"0": ["nonmob", {"permeability": 0, "id": "default:nonmob:stone"}]}]}], [{"layers": [{"0": ["nonmob", {"permeability": 0, "id": "default:nonmob:stone"}]}, {"0": ["nonmob", {"permeability": 0, "id": "default:nonmob:stone"}]}]}, {"layers": [{"0": ["nonmob", {"permeability": 0, "id": "default:nonmob:grass"}]}]}, {"layers": [{"0": ["nonmob", {"permeability": 0, "id": "default:nonmob:grass"}]}]}, {"layers": [{"0": ["nonmob", {"permeability": 0, "id": "default:nonmob:grass"}]}]}, {"layers": [{"0": ["nonmob", {"permeability": 0, "id": "default:nonmob:grass"}]}]}, {"layers": [{"0": ["nonmob", {"permeability": 0, "id": "default:nonmob:grass"}]}]}, {"layers": [{"0": ["nonmob", {"permeability": 0, "id": "default:nonmob:grass"}]}]}, {"layers": [{"0": ["nonmob", {"permeability": 0, "id": "default:nonmob:grass"}]}]}, {"layers": [{"0": ["nonmob", {"permeability": 0, "id": "default:nonmob:grass"}]}]}, {"layers": [{"0": ["nonmob", {"permeability": 0, "id": "default:nonmob:grass"}]}]}, {"layers": [{"0": ["nonmob", {"permeability": 0, "id": "default:nonmob:grass"}]}]}, {"layers": [{"0": ["nonmob", {"permeability": 0, "id": "default:nonmob:grass"}]}]}, {"layers": [{"0": ["nonmob", {"permeability": 0, "id": "default:nonmob:grass"}]}]}, {"layers": [{"0": ["nonmob", {"permeability": 0, "id": "default:nonmob:grass"}]}]}, {"layers": [{"0": ["nonmob", {"permeability": 0, "id": "default:nonmob:grass"}]}]}, {"layers": [{"0": ["nonmob", {"permeability": 0, "id": "default:nonmob:stone"}]}, {"0": ["nonmob", {"permeability": 0, "id": "default:nonmob:stone"}]}]}], [{"layers": [{"0": ["nonmob", {"permeability": 0, "id": "default:nonmob:stone"}]}, {"0": ["nonmob", {"permeability": 0, "id": "default:nonmob:stone"}]}]}, {"layers": [{"0": ["nonmob", {"permeability": 0, "id": "default:nonmob:grass"}]}]}, {"layers": [{"0": ["nonmob", {"permeability": 0, "id": "default:nonmob:grass"}]}]}, {"layers": [{"0": ["nonmob", {"permeability": 0, "id": "default:nonmob:grass"}]}]}, {"layers": [{"0": ["nonmob", {"permeability": 0, "id": "default:nonmob:grass"}]}]}, {"layers": [{"0": ["nonmob", {"permeability": 0, "id": "default:nonmob:grass"}]}]}, {"layers": [{"0": ["nonmob", {"permeability": 0, "id": "default:nonmob:grass"}]}]}, {"layers": [{"0": ["nonmob", {"permeability": 0, "id": "default:nonmob:grass"}]}]}, {"layers": [{"0": ["nonmob", {"permeability": 0, "id": "default:nonmob:grass"}]}]}, {"layers": [{"0": ["nonmob", {"permeability": 0, "id": "default:nonmob:grass"}]}]}, {"layers": [{"0": ["nonmob", {"permeability": 0, "id": "default:nonmob:grass"}]}]}, {"layers": [{"0": ["nonmob", {"permeability": 0, "id": "default:nonmob:grass"}]}]}, {"layers": [{"0": ["nonmob", {"permeability": 0, "id": "default:nonmob:grass"}]}]}, {"layers": [{"0": ["nonmob", {"permeability": 0, "id": "default:nonmob:grass"}]}]}, {"layers": [{"0": ["nonmob", {"permeability": 0, "id": "default:nonmob:grass"}]}]}, {"layers": [{"0": ["nonmob", {"permeability": 0, "id": "default:nonmob:stone"}]}, {"0": ["nonmob", {"permeability": 0, "id": "default:nonmob:stone"}]}]}], [{"layers": [{"0": ["nonmob", {"permeability": 0, "id": "default:nonmob:stone"}]}, {"0": ["nonmob", {"permeability": 0, "id": "default:nonmob:stone"}]}]}, {"layers": [{"0": ["nonmob", {"permeability": 0, "id": "default:nonmob:grass"}]}]}, {"layers": [{"0": ["nonmob", {"permeability": 0, "id": "default:nonmob:grass"}]}]}, {"layers": [{"0": ["nonmob", {"permeability": 0, "id": "default:nonmob:grass"}]}]}, {"layers": [{"0": ["nonmob", {"permeability": 0, "id": "default:nonmob:grass"}]}]}, {"layers": [{"0": ["nonmob", {"permeability": 0, "id": "default:nonmob:grass"}]}]}, {"layers": [{"0": ["nonmob", {"permeability": 0, "id": "default:nonmob:grass"}]}]}, {"layers": [{"0": ["nonmob", {"permeability": 0, "id": "default:nonmob:grass"}]}]}, {"layers": [{"0": ["nonmob", {"permeability": 0, "id": "default:nonmob:grass"}]}]}, {"layers": [{"0": ["nonmob", {"permeability": 0, "id": "default:nonmob:grass"}]}]}, {"layers": [{"0": ["nonmob", {"permeability": 0, "id": "default:nonmob:grass"}]}]}, {"layers": [{"0": ["nonmob", {"permeability": 0, "id": "default:nonmob:grass"}]}]}, {"layers": [{"0": ["nonmob", {"permeability": 0, "id": "default:nonmob:grass"}]}]}, {"layers": [{"0": ["nonmob", {"permeability": 0, "id": "default:nonmob:grass"}]}]}, {"layers": [{"0": ["nonmob", {"permeability": 0, "id": "default:nonmob:grass"}]}]}, {"layers": [{"0": ["nonmob", {"permeability": 0, "id": "default:nonmob:stone"}]}, {"0": ["nonmob", {"permeability": 0, "id": "default:nonmob:stone"}]}]}], [{"layers": [{"0": ["nonmob", {"permeability": 0, "id": "default:nonmob:stone"}]}, {"0": ["nonmob", {"permeability": 0, "id": "default:nonmob:stone"}]}]}, {"layers": [{"0": ["nonmob", {"permeability": 0, "id": "default:nonmob:grass"}]}]}, {"layers": [{"0": ["nonmob", {"permeability": 0, "id": "default:nonmob:grass"}]}]}, {"layers": [{"0": ["nonmob", {"permeability": 0, "id": "default:nonmob:grass"}]}]}, {"layers": [{"0": ["nonmob", {"permeability": 0, "id": "default:nonmob:grass"}]}]}, {"layers": [{"0": ["nonmob", {"permeability": 0, "id": "default:nonmob:grass"}]}]}, {"layers": [{"0": ["nonmob", {"permeability": 0, "id": "default:nonmob:grass"}]}]}, {"layers": [{"0": ["nonmob", {"permeability": 0, "id": "default:nonmob:grass"}]}]}, {"layers": [{"0": ["nonmob", {"permeability": 0, "id": "default:nonmob:grass"}]}]}, {"layers": [{"0": ["nonmob", {"permeability": 0, "id": "default:nonmob:grass"}]}]}, {"layers": [{"0": ["nonmob", {"permeability": 0, "id": "default:nonmob:grass"}]}]}, {"layers": [{"0": ["nonmob", {"permeability": 0, "id": "default:nonmob:grass"}]}]}, {"layers": [{"0": ["nonmob", {"permeability": 0, "id": "default:nonmob:grass"}]}]}, {"layers": [{"0": ["nonmob", {"permeability": 0, "id": "default:nonmob:grass"}]}]}, {"layers": [{"0": ["nonmob", {"permeability": 0, "id": "default:nonmob:grass"}]}]}, {"layers": [{"0": ["nonmob", {"permeability": 0, "id": "default:nonmob:stone"}]}, {"0": ["nonmob", {"permeability": 0, "id": "default:nonmob:stone"}]}]}], [{"layers": [{"0": ["nonmob", {"permeability": 0, "id": "default:nonmob:stone"}]}, {"0": ["nonmob", {"permeability": 0, "id": "default:nonmob:stone"}]}]}, {"layers": [{"0": ["nonmob", {"permeability": 0, "id": "default:nonmob:grass"}]}]}, {"layers": [{"0": ["nonmob", {"permeability": 0, "id": "default:nonmob:grass"}]}]}, {"layers": [{"0": ["nonmob", {"permeability": 0, "id": "default:nonmob:grass"}]}]}, {"layers": [{"0": ["nonmob", {"permeability": 0, "id": "default:nonmob:grass"}]}]}, {"layers": [{"0": ["nonmob", {"permeability": 0, "id": "default:nonmob:grass"}]}]}, {"layers": [{"0": ["nonmob", {"permeability": 0, "id": "default:nonmob:grass"}]}]}, {"layers": [{"0": ["nonmob", {"permeability": 0, "id": "default:nonmob:grass"}]}]}, {"layers": [{"0": ["nonmob", {"permeability": 0, "id": "default:nonmob:grass"}]}]}, {"layers": [{"0": ["nonmob", {"permeability": 0, "id": "default:nonmob:grass"}]}]}, {"layers": [{"0": ["nonmob", {"permeability": 0, "id": "default:nonmob:grass"}]}]}, {"layers": [{"0": ["nonmob", {"permeability": 0, "id": "default:nonmob:grass"}]}]}, {"layers": [{"0": ["nonmob", {"permeability": 0, "id": "default:nonmob:grass"}]}]}, {"layers": [{"0": ["nonmob", {"permeability": 0, "id": "default:nonmob:grass"}]}]}, {"layers": [{"0": ["nonmob", {"permeability": 0, "id": "default:nonmob:grass"}]}]}, {"layers": [{"0": ["nonmob", {"permeability": 0, "id": "default:nonmob:stone"}]}, {"0": ["nonmob", {"permeability": 0, "id": "default:nonmob:stone"}]}]}], [{"layers": [{"0": ["nonmob", {"permeability": 0, "id": "default:nonmob:stone"}]}, {"0": ["nonmob", {"permeability": 0, "id": "default:nonmob:stone"}]}]}, {"layers": [{"0": ["nonmob", {"permeability": 0, "id": "default:nonmob:grass"}]}]}, {"layers": [{"0": ["nonmob", {"permeability": 0, "id": "default:nonmob:grass"}]}]}, {"layers": [{"0": ["nonmob", {"permeability": 0, "id": "default:nonmob:grass"}]}]}, {"layers": [{"0": ["nonmob", {"permeability": 0, "id": "default:nonmob:grass"}]}]}, {"layers": [{"0": ["nonmob", {"permeability": 0, "id": "default:nonmob:grass"}]}]}, {"layers": [{"0": ["nonmob", {"permeability": 0, "id": "default:nonmob:grass"}]}]}, {"layers": [{"0": ["nonmob", {"permeability": 0, "id": "default:nonmob:grass"}]}]}, {"layers": [{"0": ["nonmob", {"permeability": 0, "id": "default:nonmob:grass"}]}]}, {"layers": [{"0": ["nonmob", {"permeability": 0, "id": "default:nonmob:grass"}]}]}, {"layers": [{"0": ["nonmob", {"permeability": 0, "id": "default:nonmob:grass"}]}]}, {"layers": [{"0": ["nonmob", {"permeability": 0, "id": "default:nonmob:grass"}]}]}, {"layers": [{"0": ["nonmob", {"permeability": 0, "id": "default:nonmob:grass"}]}]}, {"layers": [{"0": ["nonmob", {"permeability": 0, "id": "default:nonmob:grass"}]}]}, {"layers": [{"0": ["nonmob", {"permeability": 0, "id": "default:nonmob:grass"}]}]}, {"layers": [{"0": ["nonmob", {"permeability": 0, "id": "default:nonmob:stone"}]}, {"0": ["nonmob", {"permeability": 0, "id": "default:nonmob:stone"}]}]}], [{"layers": [{"0": ["nonmob", {"permeability": 0, "id": "default:nonmob:stone"}]}, {"0": ["nonmob", {"permeability": 0, "id": "default:nonmob:stone"}]}]}, {"layers": [{"0": ["nonmob", {"permeability": 0, "id": "default:nonmob:grass"}]}]}, {"layers": [{"0": ["nonmob", {"permeability": 0, "id": "default:nonmob:grass"}]}]}, {"layers": [{"0": ["nonmob", {"permeability": 0, "id": "default:nonmob:grass"}]}]}, {"layers": [{"0": ["nonmob", {"permeability": 0, "id": "default:nonmob:grass"}]}]}, {"layers": [{"0": ["nonmob", {"permeability": 0, "id": "default:nonmob:grass"}]}]}, {"layers": [{"0": ["nonmob", {"permeability": 0, "id": "default:nonmob:grass"}]}]}, {"layers": [{"0": ["nonmob", {"permeability": 0, "id": "default:nonmob:grass"}]}]}, {"layers": [{"0": ["nonmob", {"permeability": 0, "id": "default:nonmob:grass"}]}]}, {"layers": [{"0": ["nonmob", {"permeability": 0, "id": "default:nonmob:grass"}]}]}, {"layers": [{"0": ["nonmob", {"permeability": 0, "id": "default:nonmob:grass"}]}]}, {"layers": [{"0": ["nonmob", {"permeability": 0, "id": "default:nonmob:grass"}]}]}, {"layers": [{"0": ["nonmob", {"permeability": 0, "id": "default:nonmob:grass"}]}]}, {"layers": [{"0": ["nonmob", {"permeability": 0, "id": "default:nonmob:grass"}]}]}, {"layers": [{"0": ["nonmob", {"permeability": 0, "id": "default:nonmob:grass"}]}]}, {"layers": [{"0": ["nonmob", {"permeability": 0, "id": "default:nonmob:stone"}]}, {"0": ["nonmob", {"permeability": 0, "id": "default:nonmob:stone"}]}]}], [{"layers": [{"0": ["nonmob", {"permeability": 0, "id": "default:nonmob:stone"}]}, {"0": ["nonmob", {"permeability": 0, "id": "default:nonmob:stone"}]}]}, {"layers": [{"0": ["nonmob", {"permeability": 0, "id": "default:nonmob:grass"}]}]}, {"layers": [{"0": ["nonmob", {"permeability": 0, "id": "default:nonmob:grass"}]}]}, {"layers": [{"0": ["nonmob", {"permeability": 0, "id": "default:nonmob:grass"}]}]}, {"layers": [{"0": ["nonmob", {"permeability": 0, "id": "default:nonmob:grass"}]}]}, {"layers": [{"0": ["nonmob", {"permeability": 0, "id": "default:nonmob:grass"}]}]}, {"layers": [{"0": ["nonmob", {"permeability": 0, "id": "default:nonmob:grass"}]}]}, {"layers": [{"0": ["nonmob", {"permeability": 0, "id": "default:nonmob:grass"}]}]}, {"layers": [{"0": ["nonmob", {"permeability": 0, "id": "default:nonmob:grass"}]}]}, {"layers": [{"0": ["nonmob", {"permeability": 0, "id": "default:nonmob:grass"}]}]}, {"layers": [{"0": ["nonmob", {"permeability": 0, "id": "default:nonmob:grass"}]}]}, {"layers": [{"0": ["nonmob", {"permeability": 0, "id": "default:nonmob:grass"}]}]}, {"layers": [{"0": ["nonmob", {"permeability": 0, "id": "default:nonmob:grass"}]}]}, {"layers": [{"0": ["nonmob", {"permeability": 0, "id": "default:nonmob:grass"}]}]}, {"layers": [{"0": ["nonmob", {"permeability": 0, "id": "default:nonmob:grass"}]}]}, {"layers": [{"0": ["nonmob", {"permeability": 0, "id": "default:nonmob:stone"}]}, {"0": ["nonmob", {"permeability": 0, "id": "default:nonmob:stone"}]}]}], [{"layers": [{"0": ["nonmob", {"permeability": 0, "id": "default:nonmob:stone"}]}, {"0": ["nonmob", {"permeability": 0, "id": "default:nonmob:stone"}]}]}, {"layers": [{"0": ["nonmob", {"permeability": 0, "id": "default:nonmob:grass"}]}]}, {"layers": [{"0": ["nonmob", {"permeability": 0, "id": "default:nonmob:grass"}]}]}, {"layers": [{"0": ["nonmob", {"permeability": 0, "id": "default:nonmob:grass"}]}]}, {"layers": [{"0": ["nonmob", {"permeability": 0, "id": "default:nonmob:grass"}]}]}, {"layers": [{"0": ["nonmob", {"permeability": 0, "id": "default:nonmob:grass"}]}]}, {"layers": [{"0": ["nonmob", {"permeability": 0, "id": "default:nonmob:grass"}]}]}, {"layers": [{"0": ["nonmob", {"permeability": 0, "id": "default:nonmob:grass"}]}]}, {"layers": [{"0": ["nonmob", {"permeability": 0, "id": "default:nonmob:grass"}]}]}, {"layers": [{"0": ["nonmob", {"permeability": 0, "id": "default:nonmob:grass"}]}]}, {"layers": [{"0": ["nonmob", {"permeability": 0, "id": "default:nonmob:grass"}]}]}, {"layers": [{"0": ["nonmob", {"permeability": 0, "id": "default:nonmob:grass"}]}]}, {"layers": [{"0": ["nonmob", {"permeability": 0, "id": "default:nonmob:grass"}]}]}, {"layers": [{"0": ["nonmob", {"permeability": 0, "id": "default:nonmob:grass"}]}]}, {"layers": [{"0": ["nonmob", {"permeability": 0, "id": "default:nonmob:grass"}]}]}, {"layers": [{"0": ["nonmob", {"permeability": 0, "id": "default:nonmob:stone"}]}, {"0": ["nonmob", {"permeability": 0, "id": "default:nonmob:stone"}]}]}], [{"layers": [{"0": ["nonmob", {"permeability": 0, "id": "default:nonmob:stone"}]}, {"0": ["nonmob", {"permeability": 0, "id": "default:nonmob:stone"}]}]}, {"layers": [{"0": ["nonmob", {"permeability": 0, "id": "default:nonmob:grass"}]}]}, {"layers": [{"0": ["nonmob", {"permeability": 0, "id": "default:nonmob:grass"}]}]}, {"layers": [{"0": ["nonmob", {"permeability": 0, "id": "default:nonmob:grass"}]}]}, {"layers": [{"0": ["nonmob", {"permeability": 0, "id": "default:nonmob:grass"}]}]}, {"layers": [{"0": ["nonmob", {"permeability": 0, "id": "default:nonmob:grass"}]}]}, {"layers": [{"0": ["nonmob", {"permeability": 0, "id": "default:nonmob:grass"}]}]}, {"layers": [{"0": ["nonmob", {"permeability": 0, "id": "default:nonmob:grass"}]}]}, {"layers": [{"0": ["nonmob", {"permeability": 0, "id": "default:nonmob:grass"}]}]}, {"layers": [{"0": ["nonmob", {"permeability": 0, "id": "default:nonmob:grass"}]}]}, {"layers": [{"0": ["nonmob", {"permeability": 0, "id": "default:nonmob:grass"}]}]}, {"layers": [{"0": ["nonmob", {"permeability": 0, "id": "default:nonmob:grass"}]}]}, {"layers": [{"0": ["nonmob", {"permeability": 0, "id": "default:nonmob:grass"}]}]}, {"layers": [{"0": ["nonmob", {"permeability": 0, "id": "default:nonmob:grass"}]}]}, {"layers": [{"0": ["nonmob", {"permeability": 0, "id": "default:nonmob:grass"}]}]}, {"layers": [{"0": ["nonmob", {"permeability": 0, "id": "default:nonmob:stone"}]}, {"0": ["nonmob", {"permeability": 0, "id": "default:nonmob:stone"}]}]}], [{"layers": [{"0": ["nonmob", {"permeability": 0, "id": "default:nonmob:stone"}]}, {"0": ["nonmob", {"permeability": 0, "id": "default:nonmob:stone"}]}]}, {"layers": [{"0": ["nonmob", {"permeability": 0, "id": "default:nonmob:grass"}]}]}, {"layers": [{"0": ["nonmob", {"permeability": 0, "id": "default:nonmob:grass"}]}]}, {"layers": [{"0": ["nonmob", {"permeability": 0, "id": "default:nonmob:grass"}]}]}, {"layers": [{"0": ["nonmob", {"permeability": 0, "id": "default:nonmob:grass"}]}]}, {"layers": [{"0": ["nonmob", {"permeability": 0, "id": "default:nonmob:grass"}]}]}, {"layers": [{"0": ["nonmob", {"permeability": 0, "id": "default:nonmob:grass"}]}]}, {"layers": [{"0": ["nonmob", {"permeability": 0, "id": "default:nonmob:grass"}]}]}, {"layers": [{"0": ["nonmob", {"permeability": 0, "id": "default:nonmob:grass"}]}]}, {"layers": [{"0": ["nonmob", {"permeability": 0, "id": "default:nonmob:grass"}]}]}, {"layers": [{"0": ["nonmob", {"permeability": 0, "id": "default:nonmob:grass"}]}]}, {"layers": [{"0": ["nonmob", {"permeability": 0, "id": "default:nonmob:grass"}]}]}, {"layers": [{"0": ["nonmob", {"permeability": 0, "id": "default:nonmob:grass"}]}]}, {"layers": [{"0": ["nonmob", {"permeability": 0, "id": "default:nonmob:grass"}]}]}, {"layers": [{"0": ["nonmob", {"permeability": 0, "id": "default:nonmob:grass"}]}]}, {"layers": [{"0": ["nonmob", {"permeability": 0, "id": "default:nonmob:stone"}]}, {"0": ["nonmob", {"permeability": 0, "id": "default:nonmob:stone"}]}]}], [{"layers": [{"0": ["nonmob", {"permeability": 0, "id": "default:nonmob:stone"}]}, {"0": ["nonmob", {"permeability": 0, "id": "default:nonmob:stone"}]}]}, {"layers": [{"0": ["nonmob", {"permeability": 0, "id": "default:nonmob:grass"}]}]}, {"layers": [{"0": ["nonmob", {"permeability": 0, "id": "default:nonmob:grass"}]}]}, {"layers": [{"0": ["nonmob", {"permeability": 0, "id": "default:nonmob:grass"}]}]}, {"layers": [{"0": ["nonmob", {"permeability": 0, "id": "default:nonmob:grass"}]}]}, {"layers": [{"0": ["nonmob", {"permeability": 0, "id": "default:nonmob:grass"}]}]}, {"layers": [{"0": ["nonmob", {"permeability": 0, "id": "default:nonmob:grass"}]}]}, {"layers": [{"0": ["nonmob", {"permeability": 0, "id": "default:nonmob:grass"}]}]}, {"layers": [{"0": ["nonmob", {"permeability": 0, "id": "default:nonmob:grass"}]}]}, {"layers": [{"0": ["nonmob", {"permeability": 0, "id": "default:nonmob:grass"}]}]}, {"layers": [{"0": ["nonmob", {"permeability": 0, "id": "default:nonmob:grass"}]}]}, {"layers": [{"0": ["nonmob", {"permeability": 0, "id": "default:nonmob:grass"}]}]}, {"layers": [{"0": ["nonmob", {"permeability": 0, "id": "default:nonmob:grass"}]}]}, {"layers": [{"0": ["nonmob", {"permeability": 0, "id": "default:nonmob:grass"}]}]}, {"layers": [{"0": ["nonmob", {"permeability": 0, "id": "default:nonmob:grass"}]}]}, {"layers": [{"0": ["nonmob", {"permeability": 0, "id": "default:nonmob:stone"}]}, {"0": ["nonmob", {"permeability": 0, "id": "default:nonmob:stone"}]}]}], [{"layers": [{"0": ["nonmob", {"permeability": 0, "id": "default:nonmob:stone"}]}, {"0": ["nonmob", {"permeability": 0, "id": "default:nonmob:stone"}]}]}, {"layers": [{"0": ["nonmob", {"permeability": 0, "id": "default:nonmob:grass"}]}]}, {"layers": [{"0": ["nonmob", {"permeability": 0, "id": "default:nonmob:grass"}]}]}, {"layers": [{"0": ["nonmob", {"permeability": 0, "id": "default:nonmob:grass"}]}]}, {"layers": [{"0": ["nonmob", {"permeability": 0, "id": "default:nonmob:grass"}]}]}, {"layers": [{"0": ["nonmob", {"permeability": 0, "id": "default:nonmob:grass"}]}]}, {"layers": [{"0": ["nonmob", {"permeability": 0, "id": "default:nonmob:grass"}]}]}, {"layers": [{"0": ["nonmob", {"permeability": 0, "id": "default:nonmob:grass"}]}]}, {"layers": [{"0": ["nonmob", {"permeability": 0, "id": "default:nonmob:grass"}]}]}, {"layers": [{"0": ["nonmob", {"permeability": 0, "id": "default:nonmob:grass"}]}]}, {"layers": [{"0": ["nonmob", {"permeability": 0, "id": "default:nonmob:grass"}]}]}, {"layers": [{"0": ["nonmob", {"permeability": 0, "id": "default:nonmob:grass"}]}]}, {"layers": [{"0": ["nonmob", {"permeability": 0, "id": "default:nonmob:grass"}]}]}, {"layers": [{"0": ["nonmob", {"permeability": 0, "id": "default:nonmob:grass"}]}]}, {"layers": [{"0": ["nonmob", {"permeability": 0, "id": "default:nonmob:grass"}]}]}, {"layers": [{"0": ["nonmob", {"permeability": 0, "id": "default:nonmob:stone"}]}, {"0": ["nonmob", {"permeability": 0, "id": "default:nonmob:stone"}]}]}], [{"layers": [{"0": ["nonmob", {"permeability": 0, "id": "default:nonmob:stone"}]}, {"0": ["nonmob", {"permeability": 0, "id": "default:nonmob:stone"}]}]}, {"layers": [{"0": ["nonmob", {"permeability": 0, "id": "default:nonmob:grass"}]}]}, {"layers": [{"0": ["nonmob", {"permeability": 0, "id": "default:nonmob:grass"}]}]}, {"layers": [{"0": ["nonmob", {"permeability": 0, "id": "default:nonmob:grass"}]}]}, {"layers": [{"0": ["nonmob", {"permeability": 0, "id": "default:nonmob:grass"}]}]}, {"layers": [{"0": ["nonmob", {"permeability": 0, "id": "default:nonmob:grass"}]}]}, {"layers": [{"0": ["nonmob", {"permeability": 0, "id": "default:nonmob:grass"}]}]}, {"layers": [{"0": ["nonmob", {"permeability": 0, "id": "default:nonmob:grass"}]}]}, {"layers": [{"0": ["nonmob", {"permeability": 0, "id": "default:nonmob:grass"}]}]}, {"layers": [{"0": ["nonmob", {"permeability": 0, "id": "default:nonmob:grass"}]}]}, {"layers": [{"0": ["nonmob", {"permeability": 0, "id": "default:nonmob:grass"}]}]}, {"layers": [{"0": ["nonmob", {"permeability": 0, "id": "default:nonmob:grass"}]}]}, {"layers": [{"0": ["nonmob", {"permeability": 0, "id": "default:nonmob:grass"}]}]}, {"layers": [{"0": ["nonmob", {"permeability": 0, "id": "default:nonmob:grass"}]}]}, {"layers": [{"0": ["nonmob", {"permeability": 0, "id": "default:nonmob:grass"}]}]}, {"layers": [{"0": ["nonmob", {"permeability": 0, "id": "default:nonmob:stone"}]}, {"0": ["nonmob", {"permeability": 0, "id": "default:nonmob:stone"}]}]}], [{"layers": [{"0": ["nonmob", {"permeability": 0, "id": "default:nonmob:stone"}]}, {"0": ["nonmob", {"permeability": 0, "id": "default:nonmob:stone"}]}]}, {"layers": [{"0": ["nonmob", {"permeability": 0, "id": "default:nonmob:grass"}]}]}, {"layers": [{"0": ["nonmob", {"permeability": 0, "id": "default:nonmob:grass"}]}]}, {"layers": [{"0": ["nonmob", {"permeability": 0, "id": "default:nonmob:grass"}]}]}, {"layers": [{"0": ["nonmob", {"permeability": 0, "id": "default:nonmob:grass"}]}]}, {"layers": [{"0": ["nonmob", {"permeability": 0, "id": "default:nonmob:grass"}]}]}, {"layers": [{"0": ["nonmob", {"permeability": 0, "id": "default:nonmob:grass"}]}]}, {"layers": [{"0": ["nonmob", {"permeability": 0, "id": "default:nonmob:grass"}]}]}, {"layers": [{"0": ["nonmob", {"permeability": 0, "id": "default:nonmob:grass"}]}]}, {"layers": [{"0": ["nonmob", {"permeability": 0, "id": "default:nonmob:grass"}]}]}, {"layers": [{"0": ["nonmob", {"permeability": 0, "id": "default:nonmob:grass"}]}]}, {"layers": [{"0": ["nonmob", {"permeability": 0, "id": "default:nonmob:grass"}]}]}, {"layers": [{"0": ["nonmob", {"permeability": 0, "id": "default:nonmob:grass"}]}]}, {"layers": [{"0": ["nonmob", {"permeability": 0, "id": "default:nonmob:grass"}]}]}, {"layers": [{"0": ["nonmob", {"permeability": 0, "id": "default:nonmob:grass"}]}]}, {"layers": [{"0": ["nonmob", {"permeability": 0, "id": "default:nonmob:stone"}]}, {"0": ["nonmob", {"permeability": 0, "id": "default:nonmob:stone"}]}]}], [{"layers": [{"0": ["nonmob", {"permeability": 0, "id": "default:nonmob:stone"}]}, {"0": ["nonmob", {"permeability": 0, "id": "default:nonmob:stone"}]}]}, {"layers": [{"0": ["nonmob", {"permeability": 0, "id": "default:nonmob:grass"}]}]}, {"layers": [{"0": ["nonmob", {"permeability": 0, "id": "default:nonmob:grass"}]}]}, {"layers": [{"0": ["nonmob", {"permeability": 0, "id": "default:nonmob:grass"}]}]}, {"layers": [{"0": ["nonmob", {"permeability": 0, "id": "default:nonmob:grass"}]}]}, {"layers": [{"0": ["nonmob", {"permeability": 0, "id": "default:nonmob:grass"}]}]}, {"layers": [{"0": ["nonmob", {"permeability": 0, "id": "default:nonmob:grass"}]}]}, {"layers": [{"0": ["nonmob", {"permeability": 0, "id": "default:nonmob:grass"}]}]}, {"layers": [{"0": ["nonmob", {"permeability": 0, "id": "default:nonmob:grass"}]}]}, {"layers": [{"0": ["nonmob", {"permeability": 0, "id": "default:nonmob:grass"}]}]}, {"layers": [{"0": ["nonmob", {"permeability": 0, "id": "default:nonmob:grass"}]}]}, {"layers": [{"0": ["nonmob", {"permeability": 0, "id": "default:nonmob:grass"}]}]}, {"layers": [{"0": ["nonmob", {"permeability": 0, "id": "default:nonmob:grass"}]}]}, {"layers": [{"0": ["nonmob", {"permeability": 0, "id": "default:nonmob:grass"}]}]}, {"layers": [{"0": ["nonmob", {"permeability": 0, "id": "default:nonmob:grass"}]}]}, {"layers": [{"0": ["nonmob", {"permeability": 0, "id": "default:nonmob:stone"}]}, {"0": ["nonmob", {"permeability": 0, "id": "default:nonmob:stone"}]}]}], [{"layers": [{"0": ["nonmob", {"permeability": 0, "id": "default:nonmob:stone"}]}, {"0": ["nonmob", {"permeability": 0, "id": "default:nonmob:stone"}]}]}, {"layers": [{"0": ["nonmob", {"permeability": 0, "id": "default:nonmob:grass"}]}]}, {"layers": [{"0": ["nonmob", {"permeability": 0, "id": "default:nonmob:grass"}]}]}, {"layers": [{"0": ["nonmob", {"permeability": 0, "id": "default:nonmob:grass"}]}]}, {"layers": [{"0": ["nonmob", {"permeability": 0, "id": "default:nonmob:grass"}]}]}, {"layers": [{"0": ["nonmob", {"permeability": 0, "id": "default:nonmob:grass"}]}]}, {"layers": [{"0": ["nonmob", {"permeability": 0, "id": "default:nonmob:grass"}]}]}, {"layers": [{"0": ["nonmob", {"permeability": 0, "id": "default:nonmob:grass"}]}]}, {"layers": [{"0": ["nonmob", {"permeability": 0, "id": "default:nonmob:grass"}]}]}, {"layers": [{"0": ["nonmob", {"permeability": 0, "id": "default:nonmob:grass"}]}]}, {"layers": [{"0": ["nonmob", {"permeability": 0, "id": "default:nonmob:grass"}]}]}, {"layers": [{"0": ["nonmob", {"permeability": 0, "id": "default:nonmob:grass"}]}]}, {"layers": [{"0": ["nonmob", {"permeability": 0, "id": "default:nonmob:grass"}]}]}, {"layers": [{"0": ["nonmob", {"permeability": 0, "id": "default:nonmob:grass"}]}]}, {"layers": [{"0": ["nonmob", {"permeability": 0, "id": "default:nonmob:grass"}]}]}, {"layers": [{"0": ["nonmob", {"permeability": 0, "id": "default:nonmob:stone"}]}, {"0": ["nonmob", {"permeability": 0, "id": "default:nonmob:stone"}]}]}], [{"layers": [{"0": ["nonmob", {"permeability": 0, "id": "default:nonmob:stone"}]}, {"0": ["nonmob", {"permeability": 0, "id": "default:nonmob:stone"}]}]}, {"layers": [{"0": ["nonmob", {"permeability": 0, "id": "default:nonmob:grass"}]}]}, {"layers": [{"0": ["nonmob", {"permeability": 0, "id": "default:nonmob:grass"}]}]}, {"layers": [{"0": ["nonmob", {"permeability": 0, "id": "default:nonmob:grass"}]}]}, {"layers": [{"0": ["nonmob", {"permeability": 0, "id": "default:nonmob:grass"}]}]}, {"layers": [{"0": ["nonmob", {"permeability": 0, "id": "default:nonmob:grass"}]}]}, {"layers": [{"0": ["nonmob", {"permeability": 0, "id": "default:nonmob:grass"}]}]}, {"layers": [{"0": ["nonmob", {"permeability": 0, "id": "default:nonmob:grass"}]}]}, {"layers": [{"0": ["nonmob", {"permeability": 0, "id": "default:nonmob:grass"}]}]}, {"layers": [{"0": ["nonmob", {"permeability": 0, "id": "default:nonmob:grass"}]}]}, {"layers": [{"0": ["nonmob", {"permeability": 0, "id": "default:nonmob:grass"}]}]}, {"layers": [{"0": ["nonmob", {"permeability": 0, "id": "default:nonmob:grass"}]}]}, {"layers": [{"0": ["nonmob", {"permeability": 0, "id": "default:nonmob:grass"}]}]}, {"layers": [{"0": ["nonmob", {"permeability": 0, "id": "default:nonmob:grass"}]}]}, {"layers": [{"0": ["nonmob", {"permeability": 0, "id": "default:nonmob:grass"}]}]}, {"layers": [{"0": ["nonmob", {"permeability": 0, "id": "default:nonmob:stone"}]}, {"0": ["nonmob", {"permeability": 0, "id": "default:nonmob:stone"}]}]}], [{"layers": [{"0": ["nonmob", {"permeability": 0, "id": "default:nonmob:stone"}]}, {"0": ["nonmob", {"permeability": 0, "id": "default:nonmob:stone"}]}]}, {"layers": [{"0": ["nonmob", {"permeability": 0, "id": "default:nonmob:grass"}]}]}, {"layers": [{"0": ["nonmob", {"permeability": 0, "id": "default:nonmob:grass"}]}]}, {"layers": [{"0": ["nonmob", {"permeability": 0, "id": "default:nonmob:grass"}]}]}, {"layers": [{"0": ["nonmob", {"permeability": 0, "id": "default:nonmob:grass"}]}]}, {"layers": [{"0": ["nonmob", {"permeability": 0, "id": "default:nonmob:grass"}]}]}, {"layers": [{"0": ["nonmob", {"permeability": 0, "id": "default:nonmob:grass"}]}]}, {"layers": [{"0": ["nonmob", {"permeability": 0, "id": "default:nonmob:grass"}]}]}, {"layers": [{"0": ["nonmob", {"permeability": 0, "id": "default:nonmob:grass"}]}]}, {"layers": [{"0": ["nonmob", {"permeability": 0, "id": "default:nonmob:grass"}]}]}, {"layers": [{"0": ["nonmob", {"permeability": 0, "id": "default:nonmob:grass"}]}]}, {"layers": [{"0": ["nonmob", {"permeability": 0, "id": "default:nonmob:grass"}]}]}, {"layers": [{"0": ["nonmob", {"permeability": 0, "id": "default:nonmob:grass"}]}]}, {"layers": [{"0": ["nonmob", {"permeability": 0, "id": "default:nonmob:grass"}]}]}, {"layers": [{"0": ["nonmob", {"permeability": 0, "id": "default:nonmob:grass"}]}]}, {"layers": [{"0": ["nonmob", {"permeability": 0, "id": "default:nonmob:stone"}]}, {"0": ["nonmob", {"permeability": 0, "id": "default:nonmob:stone"}]}]}], [{"layers": [{"0": ["nonmob", {"permeability": 0, "id": "default:nonmob:stone"}]}, {"0": ["nonmob", {"permeability": 0, "id": "default:nonmob:stone"}]}]}, {"layers": [{"0": ["nonmob", {"permeability": 0, "id": "default:nonmob:grass"}]}]}, {"layers": [{"0": ["nonmob", {"permeability": 0, "id": "default:nonmob:grass"}]}]}, {"layers": [{"0": ["nonmob", {"permeability": 0, "id": "default:nonmob:grass"}]}]}, {"layers": [{"0": ["nonmob", {"permeability": 0, "id": "default:nonmob:grass"}]}]}, {"layers": [{"0": ["nonmob", {"permeability": 0, "id": "default:nonmob:grass"}]}]}, {"layers": [{"0": ["nonmob", {"permeability": 0, "id": "default:nonmob:grass"}]}]}, {"layers": [{"0": ["nonmob", {"permeability": 0, "id": "default:nonmob:grass"}]}]}, {"layers": [{"0": ["nonmob", {"permeability": 0, "id": "default:nonmob:grass"}]}]}, {"layers": [{"0": ["nonmob", {"permeability": 0, "id": "default:nonmob:grass"}]}]}, {"layers": [{"0": ["nonmob", {"permeability": 0, "id": "default:nonmob:grass"}]}]}, {"layers": [{"0": ["nonmob", {"permeability": 0, "id": "default:nonmob:grass"}]}]}, {"layers": [{"0": ["nonmob", {"permeability": 0, "id": "default:nonmob:grass"}]}]}, {"layers": [{"0": ["nonmob", {"permeability": 0, "id": "default:nonmob:grass"}]}]}, {"layers": [{"0": ["nonmob", {"permeability": 0, "id": "default:nonmob:grass"}]}]}, {"layers": [{"0": ["nonmob", {"permeability": 0, "id": "default:nonmob:stone"}]}, {"0": ["nonmob", {"permeability": 0, "id": "default:nonmob:stone"}]}]}], [{"layers": [{"0": ["nonmob", {"permeability": 0, "id": "default:nonmob:stone"}]}, {"0": ["nonmob", {"permeability": 0, "id": "default:nonmob:stone"}]}]}, {"layers": [{"0": ["nonmob", {"permeability": 0, "id": "default:nonmob:grass"}]}]}, {"layers": [{"0": ["nonmob", {"permeability": 0, "id": "default:nonmob:grass"}]}]}, {"layers": [{"0": ["nonmob", {"permeability": 0, "id": "default:nonmob:grass"}]}]}, {"layers": [{"0": ["nonmob", {"permeability": 0, "id": "default:nonmob:grass"}]}]}, {"layers": [{"0": ["nonmob", {"permeability": 0, "id": "default:nonmob:grass"}]}]}, {"layers": [{"0": ["nonmob", {"permeability": 0, "id": "default:nonmob:grass"}]}]}, {"layers": [{"0": ["nonmob", {"permeability": 0, "id": "default:nonmob:grass"}]}]}, {"layers": [{"0": ["nonmob", {"permeability": 0, "id": "default:nonmob:grass"}]}]}, {"layers": [{"0": ["nonmob", {"permeability": 0, "id": "default:nonmob:grass"}]}]}, {"layers": [{"0": ["nonmob", {"permeability": 0, "id": "default:nonmob:grass"}]}]}, {"layers": [{"0": ["nonmob", {"permeability": 0, "id": "default:nonmob:grass"}]}]}, {"layers": [{"0": ["nonmob", {"permeability": 0, "id": "default:nonmob:grass"}]}]}, {"layers": [{"0": ["nonmob", {"permeability": 0, "id": "default:nonmob:grass"}]}]}, {"layers": [{"0": ["nonmob", {"permeability": 0, "id": "default:nonmob:grass"}]}]}, {"layers": [{"0": ["nonmob", {"permeability": 0, "id": "default:nonmob:stone"}]}, {"0": ["nonmob", {"permeability": 0, "id": "default:nonmob:stone"}]}]}], [{"layers": [{"0": ["nonmob", {"permeability": 0, "id": "default:nonmob:stone"}]}, {"0": ["nonmob", {"permeability": 0, "id": "default:nonmob:stone"}]}]}, {"layers": [{"0": ["nonmob", {"permeability": 0, "id": "default:nonmob:grass"}]}]}, {"layers": [{"0": ["nonmob", {"permeability": 0, "id": "default:nonmob:grass"}]}]}, {"layers": [{"0": ["nonmob", {"permeability": 0, "id": "default:nonmob:grass"}]}]}, {"layers": [{"0": ["nonmob", {"permeability": 0, "id": "default:nonmob:grass"}]}]}, {"layers": [{"0": ["nonmob", {"permeability": 0, "id": "default:nonmob:grass"}]}]}, {"layers": [{"0": ["nonmob", {"permeability": 0, "id": "default:nonmob:grass"}]}]}, {"layers": [{"0": ["nonmob", {"permeability": 0, "id": "default:nonmob:grass"}]}]}, {"layers": [{"0": ["nonmob", {"permeability": 0, "id": "default:nonmob:grass"}]}]}, {"layers": [{"0": ["nonmob", {"permeability": 0, "id": "default:nonmob:grass"}]}]}, {"layers": [{"0": ["nonmob", {"permeability": 0, "id": "default:nonmob:grass"}]}]}, {"layers": [{"0": ["nonmob", {"permeability": 0, "id": "default:nonmob:grass"}]}]}, {"layers": [{"0": ["nonmob", {"permeability": 0, "id": "default:nonmob:grass"}]}]}, {"layers": [{"0": ["nonmob", {"permeability": 0, "id": "default:nonmob:grass"}]}]}, {"layers": [{"0": ["nonmob", {"permeability": 0, "id": "default:nonmob:grass"}]}]}, {"layers": [{"0": ["nonmob", {"permeability": 0, "id": "default:nonmob:stone"}]}, {"0": ["nonmob", {"permeability": 0, "id": "default:nonmob:stone"}]}]}], [{"layers": [{"0": ["nonmob", {"permeability": 0, "id": "default:nonmob:stone"}]}, {"0": ["nonmob", {"permeability": 0, "id": "default:nonmob:stone"}]}]}, {"layers": [{"0": ["nonmob", {"permeability": 0, "id": "default:nonmob:grass"}]}]}, {"layers": [{"0": ["nonmob", {"permeability": 0, "id": "default:nonmob:grass"}]}]}, {"layers": [{"0": ["nonmob", {"permeability": 0, "id": "default:nonmob:grass"}]}]}, {"layers": [{"0": ["nonmob", {"permeability": 0, "id": "default:nonmob:grass"}]}]}, {"layers": [{"0": ["nonmob", {"permeability": 0, "id": "default:nonmob:grass"}]}]}, {"layers": [{"0": ["nonmob", {"permeability": 0, "id": "default:nonmob:grass"}]}]}, {"layers": [{"0": ["nonmob", {"permeability": 0, "id": "default:nonmob:grass"}]}]}, {"layers": [{"0": ["nonmob", {"permeability": 0, "id": "default:nonmob:grass"}]}]}, {"layers": [{"0": ["nonmob", {"permeability": 0, "id": "default:nonmob:grass"}]}]}, {"layers": [{"0": ["nonmob", {"permeability": 0, "id": "default:nonmob:grass"}]}]}, {"layers": [{"0": ["nonmob", {"permeability": 0, "id": "default:nonmob:grass"}]}]}, {"layers": [{"0": ["nonmob", {"permeability": 0, "id": "default:nonmob:grass"}]}]}, {"layers": [{"0": ["nonmob", {"permeability": 0, "id": "default:nonmob:grass"}]}]}, {"layers": [{"0": ["nonmob", {"permeability": 0, "id": "default:nonmob:grass"}]}]}, {"layers": [{"0": ["nonmob", {"permeability": 0, "id": "default:nonmob:stone"}]}, {"0": ["nonmob", {"permeability": 0, "id": "default:nonmob:stone"}]}]}], [{"layers": [{"0": ["nonmob", {"permeability": 0, "id": "default:nonmob:stone"}]}, {"0": ["nonmob", {"permeability": 0, "id": "default:nonmob:stone"}]}]}, {"layers": [{"0": ["nonmob", {"permeability": 0, "id": "default:nonmob:grass"}]}]}, {"layers": [{"0": ["nonmob", {"permeability": 0, "id": "default:nonmob:grass"}]}]}, {"layers": [{"0": ["nonmob", {"permeability": 0, "id": "default:nonmob:grass"}]}]}, {"layers": [{"0": ["nonmob", {"permeability": 0, "id": "default:nonmob:grass"}]}]}, {"layers": [{"0": ["nonmob", {"permeability": 0, "id": "default:nonmob:grass"}]}]}, {"layers": [{"0": ["nonmob", {"permeability": 0, "id": "default:nonmob:grass"}]}]}, {"layers": [{"0": ["nonmob", {"permeability": 0, "id": "default:nonmob:grass"}]}]}, {"layers": [{"0": ["nonmob", {"permeability": 0, "id": "default:nonmob:grass"}]}]}, {"layers": [{"0": ["nonmob", {"permeability": 0, "id": "default:nonmob:grass"}]}]}, {"layers": [{"0": ["nonmob", {"permeability": 0, "id": "default:nonmob:grass"}]}]}, {"layers": [{"0": ["nonmob", {"permeability": 0, "id": "default:nonmob:grass"}]}]}, {"layers": [{"0": ["nonmob", {"permeability": 0, "id": "default:nonmob:grass"}]}]}, {"layers": [{"0": ["nonmob", {"permeability": 0, "id": "default:nonmob:grass"}]}]}, {"layers": [{"0": ["nonmob", {"permeability": 0, "id": "default:nonmob:grass"}]}]}, {"layers": [{"0": ["nonmob", {"permeability": 0, "id": "default:nonmob:stone"}]}, {"0": ["nonmob", {"permeability": 0, "id": "default:nonmob:stone"}]}]}], [{"layers": [{"0": ["nonmob", {"permeability": 0, "id": "default:nonmob:stone"}]}, {"0": ["nonmob", {"permeability": 0, "id": "default:nonmob:stone"}]}]}, {"layers": [{"0": ["nonmob", {"permeability": 0, "id": "default:nonmob:grass"}]}]}, {"layers": [{"0": ["nonmob", {"permeability": 0, "id": "default:nonmob:grass"}]}]}, {"layers": [{"0": ["nonmob", {"permeability": 0, "id": "default:nonmob:grass"}]}]}, {"layers": [{"0": ["nonmob", {"permeability": 0, "id": "default:nonmob:grass"}]}]}, {"layers": [{"0": ["nonmob", {"permeability": 0, "id": "default:nonmob:grass"}]}]}, {"layers": [{"0": ["nonmob", {"permeability": 0, "id": "default:nonmob:grass"}]}]}, {"layers": [{"0": ["nonmob", {"permeability": 0, "id": "default:nonmob:grass"}]}]}, {"layers": [{"0": ["nonmob", {"permeability": 0, "id": "default:nonmob:grass"}]}]}, {"layers": [{"0": ["nonmob", {"permeability": 0, "id": "default:nonmob:grass"}]}]}, {"layers": [{"0": ["nonmob", {"permeability": 0, "id": "default:nonmob:grass"}]}]}, {"layers": [{"0": ["nonmob", {"permeability": 0, "id": "default:nonmob:grass"}]}]}, {"layers": [{"0": ["nonmob", {"permeability": 0, "id": "default:nonmob:grass"}]}]}, {"layers": [{"0": ["nonmob", {"permeability": 0, "id": "default:nonmob:grass"}]}]}, {"layers": [{"0": ["nonmob", {"permeability": 0, "id": "default:nonmob:grass"}]}]}, {"layers": [{"0": ["nonmob", {"permeability": 0, "id": "default:nonmob:stone"}]}, {"0": ["nonmob", {"permeability": 0, "id": "default:nonmob:stone"}]}]}], [{"layers": [{"0": ["nonmob", {"permeability": 0, "id": "default:nonmob:stone"}]}, {"0": ["nonmob", {"permeability": 0, "id": "default:nonmob:stone"}]}]}, {"layers": [{"0": ["nonmob", {"permeability": 0, "id": "default:nonmob:grass"}]}]}, {"layers": [{"0": ["nonmob", {"permeability": 0, "id": "default:nonmob:grass"}]}]}, {"layers": [{"0": ["nonmob", {"permeability": 0, "id": "default:nonmob:grass"}]}]}, {"layers": [{"0": ["nonmob", {"permeability": 0, "id": "default:nonmob:grass"}]}]}, {"layers": [{"0": ["nonmob", {"permeability": 0, "id": "default:nonmob:grass"}]}]}, {"layers": [{"0": ["nonmob", {"permeability": 0, "id": "default:nonmob:grass"}]}]}, {"layers": [{"0": ["nonmob", {"permeability": 0, "id": "default:nonmob:grass"}]}]}, {"layers": [{"0": ["nonmob", {"permeability": 0, "id": "default:nonmob:grass"}]}]}, {"layers": [{"0": ["nonmob", {"permeability": 0, "id": "default:nonmob:grass"}]}]}, {"layers": [{"0": ["nonmob", {"permeability": 0, "id": "default:nonmob:grass"}]}]}, {"layers": [{"0": ["nonmob", {"permeability": 0, "id": "default:nonmob:grass"}]}]}, {"layers": [{"0": ["nonmob", {"permeability": 0, "id": "default:nonmob:grass"}]}]}, {"layers": [{"0": ["nonmob", {"permeability": 0, "id": "default:nonmob:grass"}]}]}, {"layers": [{"0": ["nonmob", {"permeability": 0, "id": "default:nonmob:grass"}]}]}, {"layers": [{"0": ["nonmob", {"permeability": 0, "id": "default:nonmob:stone"}]}, {"0": ["nonmob", {"permeability": 0, "id": "default:nonmob:stone"}]}]}], [{"layers": [{"0": ["nonmob", {"permeability": 0, "id": "default:nonmob:stone"}]}, {"0": ["nonmob", {"permeability": 0, "id": "default:nonmob:stone"}]}]}, {"layers": [{"0": ["nonmob", {"permeability": 0, "id": "default:nonmob:grass"}]}]}, {"layers": [{"0": ["nonmob", {"permeability": 0, "id": "default:nonmob:grass"}]}]}, {"layers": [{"0": ["nonmob", {"permeability": 0, "id": "default:nonmob:grass"}]}]}, {"layers": [{"0": ["nonmob", {"permeability": 0, "id": "default:nonmob:grass"}]}]}, {"layers": [{"0": ["nonmob", {"permeability": 0, "id": "default:nonmob:grass"}]}]}, {"layers": [{"0": ["nonmob", {"permeability": 0, "id": "default:nonmob:grass"}]}]}, {"layers": [{"0": ["nonmob", {"permeability": 0, "id": "default:nonmob:grass"}]}]}, {"layers": [{"0": ["nonmob", {"permeability": 0, "id": "default:nonmob:grass"}]}]}, {"layers": [{"0": ["nonmob", {"permeability": 0, "id": "default:nonmob:grass"}]}]}, {"layers": [{"0": ["nonmob", {"permeability": 0, "id": "default:nonmob:grass"}]}]}, {"layers": [{"0": ["nonmob", {"permeability": 0, "id": "default:nonmob:grass"}]}]}, {"layers": [{"0": ["nonmob", {"permeability": 0, "id": "default:nonmob:grass"}]}]}, {"layers": [{"0": ["nonmob", {"permeability": 0, "id": "default:nonmob:grass"}]}]}, {"layers": [{"0": ["nonmob", {"permeability": 0, "id": "default:nonmob:grass"}]}]}, {"layers": [{"0": ["nonmob", {"permeability": 0, "id": "default:nonmob:stone"}]}, {"0": ["nonmob", {"permeability": 0, "id": "default:nonmob:stone"}]}]}], [{"layers": [{"0": ["nonmob", {"permeability": 0, "id": "default:nonmob:stone"}]}, {"0": ["nonmob", {"permeability": 0, "id": "default:nonmob:stone"}]}]}, {"layers": [{"0": ["nonmob", {"permeability": 0, "id": "default:nonmob:grass"}]}]}, {"layers": [{"0": ["nonmob", {"permeability": 0, "id": "default:nonmob:grass"}]}]}, {"layers": [{"0": ["nonmob", {"permeability": 0, "id": "default:nonmob:grass"}]}]}, {"layers": [{"0": ["nonmob", {"permeability": 0, "id": "default:nonmob:grass"}]}]}, {"layers": [{"0": ["nonmob", {"permeability": 0, "id": "default:nonmob:grass"}]}]}, {"layers": [{"0": ["nonmob", {"permeability": 0, "id": "default:nonmob:grass"}]}]}, {"layers": [{"0": ["nonmob", {"permeability": 0, "id": "default:nonmob:grass"}]}]}, {"layers": [{"0": ["nonmob", {"permeability": 0, "id": "default:nonmob:grass"}]}]}, {"layers": [{"0": ["nonmob", {"permeability": 0, "id": "default:nonmob:grass"}]}]}, {"layers": [{"0": ["nonmob", {"permeability": 0, "id": "default:nonmob:grass"}]}]}, {"layers": [{"0": ["nonmob", {"permeability": 0, "id": "default:nonmob:grass"}]}]}, {"layers": [{"0": ["nonmob", {"permeability": 0, "id": "default:nonmob:grass"}]}]}, {"layers": [{"0": ["nonmob", {"permeability": 0, "id": "default:nonmob:grass"}]}]}, {"layers": [{"0": ["nonmob", {"permeability": 0, "id": "default:nonmob:grass"}]}]}, {"layers": [{"0": ["nonmob", {"permeability": 0, "id": "default:nonmob:stone"}]}, {"0": ["nonmob", {"permeability": 0, "id": "default:nonmob:stone"}]}]}], [{"layers": [{"0": ["nonmob", {"permeability": 0, "id": "default:nonmob:stone"}]}, {"0": ["nonmob", {"permeability": 0, "id": "default:nonmob:stone"}]}]}, {"layers": [{"0": ["nonmob", {"permeability": 0, "id": "default:nonmob:grass"}]}]}, {"layers": [{"0": ["nonmob", {"permeability": 0, "id": "default:nonmob:grass"}]}]}, {"layers": [{"0": ["nonmob", {"permeability": 0, "id": "default:nonmob:grass"}]}]}, {"layers": [{"0": ["nonmob", {"permeability": 0, "id": "default:nonmob:grass"}]}]}, {"layers": [{"0": ["nonmob", {"permeability": 0, "id": "default:nonmob:grass"}]}]}, {"layers": [{"0": ["nonmob", {"permeability": 0, "id": "default:nonmob:grass"}]}]}, {"layers": [{"0": ["nonmob", {"permeability": 0, "id": "default:nonmob:grass"}]}]}, {"layers": [{"0": ["nonmob", {"permeability": 0, "id": "default:nonmob:grass"}]}]}, {"layers": [{"0": ["nonmob", {"permeability": 0, "id": "default:nonmob:grass"}]}]}, {"layers": [{"0": ["nonmob", {"permeability": 0, "id": "default:nonmob:grass"}]}]}, {"layers": [{"0": ["nonmob", {"permeability": 0, "id": "default:nonmob:grass"}]}]}, {"layers": [{"0": ["nonmob", {"permeability": 0, "id": "default:nonmob:grass"}]}]}, {"layers": [{"0": ["nonmob", {"permeability": 0, "id": "default:nonmob:grass"}]}]}, {"layers": [{"0": ["nonmob", {"permeability": 0, "id": "default:nonmob:grass"}]}]}, {"layers": [{"0": ["nonmob", {"permeability": 0, "id": "default:nonmob:stone"}]}, {"0": ["nonmob", {"permeability": 0, "id": "default:nonmob:stone"}]}]}], [{"layers": [{"0": ["nonmob", {"permeability": 0, "id": "default:nonmob:stone"}]}, {"0": ["nonmob", {"permeability": 0, "id": "default:nonmob:stone"}]}]}, {"layers": [{"0": ["nonmob", {"permeability": 0, "id": "default:nonmob:grass"}]}]}, {"layers": [{"0": ["nonmob", {"permeability": 0, "id": "default:nonmob:grass"}]}]}, {"layers": [{"0": ["nonmob", {"permeability": 0, "id": "default:nonmob:grass"}]}]}, {"layers": [{"0": ["nonmob", {"permeability": 0, "id": "default:nonmob:grass"}]}]}, {"layers": [{"0": ["nonmob", {"permeability": 0, "id": "default:nonmob:grass"}]}]}, {"layers": [{"0": ["nonmob", {"permeability": 0, "id": "default:nonmob:grass"}]}]}, {"layers": [{"0": ["nonmob", {"permeability": 0, "id": "default:nonmob:grass"}]}]}, {"layers": [{"0": ["nonmob", {"permeability": 0, "id": "default:nonmob:grass"}]}]}, {"layers": [{"0": ["nonmob", {"permeability": 0, "id": "default:nonmob:grass"}]}]}, {"layers": [{"0": ["nonmob", {"permeability": 0, "id": "default:nonmob:grass"}]}]}, {"layers": [{"0": ["nonmob", {"permeability": 0, "id": "default:nonmob:grass"}]}]}, {"layers": [{"0": ["nonmob", {"permeability": 0, "id": "default:nonmob:grass"}]}]}, {"layers": [{"0": ["nonmob", {"permeability": 0, "id": "default:nonmob:grass"}]}]}, {"layers": [{"0": ["nonmob", {"permeability": 0, "id": "default:nonmob:grass"}]}]}, {"layers": [{"0": ["nonmob", {"permeability": 0, "id": "default:nonmob:stone"}]}, {"0": ["nonmob", {"permeability": 0, "id": "default:nonmob:stone"}]}]}], [{"layers": [{"0": ["nonmob", {"permeability": 0, "id": "default:nonmob:stone"}]}, {"0": ["nonmob", {"permeability": 0, "id": "default:nonmob:stone"}]}]}, {"layers": [{"0": ["nonmob", {"permeability": 0, "id": "default:nonmob:grass"}]}]}, {"layers": [{"0": ["nonmob", {"permeability": 0, "id": "default:nonmob:grass"}]}]}, {"layers": [{"0": ["nonmob", {"permeability": 0, "id": "default:nonmob:grass"}]}]}, {"layers": [{"0": ["nonmob", {"permeability": 0, "id": "default:nonmob:grass"}]}]}, {"layers": [{"0": ["nonmob", {"permeability": 0, "id": "default:nonmob:grass"}]}]}, {"layers": [{"0": ["nonmob", {"permeability": 0, "id": "default:nonmob:grass"}]}]}, {"layers": [{"0": ["nonmob", {"permeability": 0, "id": "default:nonmob:grass"}]}]}, {"layers": [{"0": ["nonmob", {"permeability": 0, "id": "default:nonmob:grass"}]}]}, {"layers": [{"0": ["nonmob", {"permeability": 0, "id": "default:nonmob:grass"}]}]}, {"layers": [{"0": ["nonmob", {"permeability": 0, "id": "default:nonmob:grass"}]}]}, {"layers": [{"0": ["nonmob", {"permeability": 0, "id": "default:nonmob:grass"}]}]}, {"layers": [{"0": ["nonmob", {"permeability": 0, "id": "default:nonmob:grass"}]}]}, {"layers": [{"0": ["nonmob", {"permeability": 0, "id": "default:nonmob:grass"}]}]}, {"layers": [{"0": ["nonmob", {"permeability": 0, "id": "default:nonmob:grass"}]}]}, {"layers": [{"0": ["nonmob", {"permeability": 0, "id": "default:nonmob:stone"}]}, {"0": ["nonmob", {"permeability": 0, "id": "default:nonmob:stone"}]}]}], [{"layers": [{"0": ["nonmob", {"permeability": 0, "id": "default:nonmob:stone"}]}, {"0": ["nonmob", {"permeability": 0, "id": "default:nonmob:stone"}]}]}, {"layers": [{"0": ["nonmob", {"permeability": 0, "id": "default:nonmob:grass"}]}]}, {"layers": [{"0": ["nonmob", {"permeability": 0, "id": "default:nonmob:grass"}]}]}, {"layers": [{"0": ["nonmob", {"permeability": 0, "id": "default:nonmob:grass"}]}]}, {"layers": [{"0": ["nonmob", {"permeability": 0, "id": "default:nonmob:grass"}]}]}, {"layers": [{"0": ["nonmob", {"permeability": 0, "id": "default:nonmob:grass"}]}]}, {"layers": [{"0": ["nonmob", {"permeability": 0, "id": "default:nonmob:grass"}]}]}, {"layers": [{"0": ["nonmob", {"permeability": 0, "id": "default:nonmob:grass"}]}]}, {"layers": [{"0": ["nonmob", {"permeability": 0, "id": "default:nonmob:grass"}]}]}, {"layers": [{"0": ["nonmob", {"permeability": 0, "id": "default:nonmob:grass"}]}]}, {"layers": [{"0": ["nonmob", {"permeability": 0, "id": "default:nonmob:grass"}]}]}, {"layers": [{"0": ["nonmob", {"permeability": 0, "id": "default:nonmob:grass"}]}]}, {"layers": [{"0": ["nonmob", {"permeability": 0, "id": "default:nonmob:grass"}]}]}, {"layers": [{"0": ["nonmob", {"permeability": 0, "id": "default:nonmob:grass"}]}]}, {"layers": [{"0": ["nonmob", {"permeability": 0, "id": "default:nonmob:grass"}]}]}, {"layers": [{"0": ["nonmob", {"permeability": 0, "id": "default:nonmob:stone"}]}, {"0": ["nonmob", {"permeability": 0, "id": "default:nonmob:stone"}]}]}], [{"layers": [{"0": ["nonmob", {"permeability": 0, "id": "default:nonmob:stone"}]}, {"0": ["nonmob", {"permeability": 0, "id": "default:nonmob:stone"}]}]}, {"layers": [{"0": ["nonmob", {"permeability": 0, "id": "default:nonmob:grass"}]}]}, {"layers": [{"0": ["nonmob", {"permeability": 0, "id": "default:nonmob:grass"}]}]}, {"layers": [{"0": ["nonmob", {"permeability": 0, "id": "default:nonmob:grass"}]}]}, {"layers": [{"0": ["nonmob", {"permeability": 0, "id": "default:nonmob:grass"}]}]}, {"layers": [{"0": ["nonmob", {"permeability": 0, "id": "default:nonmob:grass"}]}]}, {"layers": [{"0": ["nonmob", {"permeability": 0, "id": "default:nonmob:grass"}]}]}, {"layers": [{"0": ["nonmob", {"permeability": 0, "id": "default:nonmob:grass"}]}]}, {"layers": [{"0": ["nonmob", {"permeability": 0, "id": "default:nonmob:grass"}]}]}, {"layers": [{"0": ["nonmob", {"permeability": 0, "id": "default:nonmob:grass"}]}]}, {"layers": [{"0": ["nonmob", {"permeability": 0, "id": "default:nonmob:grass"}]}]}, {"layers": [{"0": ["nonmob", {"permeability": 0, "id": "default:nonmob:grass"}]}]}, {"layers": [{"0": ["nonmob", {"permeability": 0, "id": "default:nonmob:grass"}]}]}, {"layers": [{"0": ["nonmob", {"permeability": 0, "id": "default:nonmob:grass"}]}]}, {"layers": [{"0": ["nonmob", {"permeability": 0, "id": "default:nonmob:grass"}]}]}, {"layers": [{"0": ["nonmob", {"permeability": 0, "id": "default:nonmob:stone"}]}, {"0": ["nonmob", {"permeability": 0, "id": "default:nonmob:stone"}]}]}], [{"layers": [{"0": ["nonmob", {"permeability": 0, "id": "default:nonmob:stone"}]}, {"0": ["nonmob", {"permeability": 0, "id": "default:nonmob:stone"}]}]}, {"layers": [{"0": ["nonmob", {"permeability": 0, "id": "default:nonmob:stone"}]}, {"0": ["nonmob", {"permeability": 0, "id": "default:nonmob:stone"}]}]}, {"layers": [{"0": ["nonmob", {"permeability": 0, "id": "default:nonmob:stone"}]}, {"0": ["nonmob", {"permeability": 0, "id": "default:nonmob:stone"}]}]}, {"layers": [{"0": ["nonmob", {"permeability": 0, "id": "default:nonmob:stone"}]}, {"0": ["nonmob", {"permeability": 0, "id": "default:nonmob:stone"}]}]}, {"layers": [{"0": ["nonmob", {"permeability": 0, "id": "default:nonmob:stone"}]}, {"0": ["nonmob", {"permeability": 0, "id": "default:nonmob:stone"}]}]}, {"layers": [{"0": ["nonmob", {"permeability": 0, "id": "default:nonmob:stone"}]}, {"0": ["nonmob", {"permeability": 0, "id": "default:nonmob:stone"}]}]}, {"layers": [{"0": ["nonmob", {"permeability": 0, "id": "default:nonmob:stone"}]}, {"0": ["nonmob", {"permeability": 0, "id": "default:nonmob:stone"}]}]}, {"layers": [{"0": ["nonmob", {"permeability": 0, "id": "default:nonmob:stone"}]}, {"0": ["nonmob", {"permeability": 0, "id": "default:nonmob:stone"}]}]}, {"layers": [{"0": ["nonmob", {"permeability": 0, "id": "default:nonmob:stone"}]}, {"0": ["nonmob", {"permeability": 0, "id": "default:nonmob:stone"}]}]}, {"layers": [{"0": ["nonmob", {"permeability": 0, "id": "default:nonmob:stone"}]}, {"0": ["nonmob", {"permeability": 0, "id": "default:nonmob:stone"}]}]}, {"layers": [{"0": ["nonmob", {"permeability": 0, "id": "default:nonmob:stone"}]}, {"0": ["nonmob", {"permeability": 0, "id": "default:nonmob:stone"}]}]}, {"layers": [{"0": ["nonmob", {"permeability": 0, "id": "default:nonmob:stone"}]}, {"0": ["nonmob", {"permeability": 0, "id": "default:nonmob:stone"}]}]}, {"layers": [{"0": ["nonmob", {"permeability": 0, "id": "default:nonmob:stone"}]}, {"0": ["nonmob", {"permeability": 0, "id": "default:nonmob:stone"}]}]}, {"layers": [{"0": ["nonmob", {"permeability": 0, "id": "default:nonmob:stone"}]}, {"0": ["nonmob", {"permeability": 0, "id": "default:nonmob:stone"}]}]}, {"layers": [{"0": ["nonmob", {"permeability": 0, "id": "default:nonmob:stone"}]}, {"0": ["nonmob", {"permeability": 0, "id": "default:nonmob:stone"}]}]}, {"layers": [{"0": ["nonmob", {"permeability": 0, "id": "default:nonmob:stone"}]}, {"0": ["nonmob", {"permeability": 0, "id": "default:nonmob:stone"}]}]}]], "size": [48, 16]},
    "index": 
        [0, [[8, 8, 1], 1]]
}